{"type": "FeatureCollection",
"features": [
{ "type": "Feature", "properties": { "DVRPC_Reg": "yes", "Cap_1": 4.000000, "Operations": "278807", "Source": "2006 DVRPC", "Helicopter": 0.000000, "Type": "AIRPORT", "Name_1": "Philadelphia International Airport", "AlternateF": "", "FacilityNa": "PHILADELPHIA INTL", "Owner": "CITY OF PHILADELPHIA", "StateName": "PENNSYLVANIA", "OBJECTID": 4, "Fcenter": 18.000000, "Cap_3": "2,315", "NAME": "Philadelphia International Airport", "County": "PHILADELPHIA", "City": "PHILADELPHIA", "REPORT": "<a href=http:\/\/www.dvrpc.org\/asp\/airport\/displayAirport.htm?id=PHL target=_blank>Facility Details<\/a>", "Owner_1": "City of Philadelphia", "Airport_Ty": "Commercial", "Ownership": "PU", "Township": "Philadelphia City, Tinicum Township", "Activity_1": 515869.000000, "FC_REPORT": "<a href=http:\/\/www.dvrpc.org\/webmaps\/PhillyFreightFinder\/reports\/FC\/FC18.pdf target=_blank>Detailed Report<\/a>" }, "geometry": { "type": "Point", "coordinates": [ -75.237550, 39.876596 ] } }
,
{ "type": "Feature", "properties": { "DVRPC_Reg": "yes", "Cap_1": 2.000000, "Operations": "12", "Source": "2006 DVRPC", "Helicopter": 33.000000, "Type": "AIRPORT", "Name_1": "Trenton-Mercer Airport", "AlternateF": "", "FacilityNa": "TRENTON MERCER", "Owner": "COUNTY OF MERCER", "StateName": "NEW JERSEY", "OBJECTID": 11, "Fcenter": 43.000000, "Cap_3": "1,345", "NAME": "Trenton Mercer Airport", "County": "MERCER", "City": "TRENTON", "REPORT": "<a href=http:\/\/www.dvrpc.org\/asp\/airport\/displayAirport.htm?id=TTN target=_blank>Facility Details<\/a>", "Owner_1": "Mercer County", "Airport_Ty": "Commercial", "Ownership": "PU", "Township": "Ewing Township", "Activity_1": 97455.000000, "FC_REPORT": "<a href=http:\/\/www.dvrpc.org\/webmaps\/PhillyFreightFinder\/reports\/FC\/FC43.pdf target=_blank>Detailed Report<\/a>" }, "geometry": { "type": "Point", "coordinates": [ -74.811872, 40.276867 ] } }

]}